wheat_yield_prediction_toolkit/__init__.py
wheat_yield_prediction_toolkit/core/__init__.py
wheat_yield_prediction_toolkit/core/bands.py
wheat_yield_prediction_toolkit/core/impute_weather_data.py
wheat_yield_prediction_toolkit/core/main.py
wheat_yield_prediction_toolkit/core/preprocessor.py
wheat_yield_prediction_toolkit/core/sat_data_collector.py
wheat_yield_prediction_toolkit/core/soil_data_collector.py
wheat_yield_prediction_toolkit/core/weather_data_collector.py
wheat_yield_prediction_toolkit/core/yield_data_collector.py
wheat_yield_prediction_toolkit/core/tmp/cb_2018_us_county_5m.dbf
wheat_yield_prediction_toolkit/core/tmp/cb_2018_us_county_5m.prj
wheat_yield_prediction_toolkit/core/tmp/cb_2018_us_county_5m.shp
wheat_yield_prediction_toolkit/core/tmp/cb_2018_us_county_5m.shp.ea.iso.xml
wheat_yield_prediction_toolkit/core/tmp/cb_2018_us_county_5m.shp.iso.xml
wheat_yield_prediction_toolkit/core/tmp/cb_2018_us_county_5m.shx
wheat_yield_prediction_toolkit/core/tmp/gz_2010_us_050_00_500k.dbf
wheat_yield_prediction_toolkit/core/tmp/gz_2010_us_050_00_500k.prj
wheat_yield_prediction_toolkit/core/tmp/gz_2010_us_050_00_500k.shp
wheat_yield_prediction_toolkit/core/tmp/gz_2010_us_050_00_500k.shx
wheat_yield_prediction_toolkit/core/tmp/gz_2010_us_050_00_500k.xml
wheat_yield_prediction_toolkit-0.1.6.dist-info/METADATA
wheat_yield_prediction_toolkit-0.1.6.dist-info/WHEEL
wheat_yield_prediction_toolkit-0.1.6.dist-info/top_level.txt
wheat_yield_prediction_toolkit-0.1.6.dist-info/RECORD
