Metadata-Version: 2.1
Name: wheat-yield-prediction-toolkit
Version: 0.1.6
Summary: Wheat Yield Prediction Toolkit is a package that provides tools for predicting wheat yield at the county level in the main wheat-producing regions of the US using deep learning approaches. The package includes modules for data collection, preprocessing, modeling, and uncertainty analysis.
Home-page: https://github.com/nour3467/wheat-yield-prediction-toolkit
Author: Noureddine Ech-chouky
Author-email: noureddineechchouky@gmail.com
Classifier: Development Status :: 3 - Alpha
Classifier: Intended Audience :: Developers
Classifier: License :: OSI Approved :: MIT License
Classifier: Programming Language :: Python :: 3.9
Requires-Python: >=3.9
Requires-Dist: tqdm
Requires-Dist: geopandas
Requires-Dist: pytest
Requires-Dist: pandas
Requires-Dist: python-dotenv
Requires-Dist: pyarrow
Requires-Dist: earthengine-api
Requires-Dist: geemap
Requires-Dist: rasterio
Requires-Dist: owslib
Requires-Dist: scienceplots
Requires-Dist: meteostat
